freebora/__init__.py
freebora/__main__.py
freebora/freebora.py
freebora/version.py
freebora-0.1.0.dist-info/DESCRIPTION.rst
freebora-0.1.0.dist-info/METADATA
freebora-0.1.0.dist-info/RECORD
freebora-0.1.0.dist-info/WHEEL
freebora-0.1.0.dist-info/entry_points.txt
freebora-0.1.0.dist-info/metadata.json
freebora-0.1.0.dist-info/top_level.txt
