Metadata-Version: 2.0
Name: freebora
Version: 0.1.0
Summary: 
Requires-Dist: aiofiles
Requires-Dist: aiohttp
Requires-Dist: lxml
Requires-Dist: requests
